MANIFEST.in
README.rst
setup.py
docs/HISTORY.txt
docs/LICENSE.GPL
docs/LICENSE.txt
docs/screenshot.png
ftw/__init__.py
ftw.globalstatusmessage.egg-info/PKG-INFO
ftw.globalstatusmessage.egg-info/SOURCES.txt
ftw.globalstatusmessage.egg-info/dependency_links.txt
ftw.globalstatusmessage.egg-info/entry_points.txt
ftw.globalstatusmessage.egg-info/namespace_packages.txt
ftw.globalstatusmessage.egg-info/not-zip-safe
ftw.globalstatusmessage.egg-info/requires.txt
ftw.globalstatusmessage.egg-info/top_level.txt
ftw/globalstatusmessage/__init__.py
ftw/globalstatusmessage/config.py
ftw/globalstatusmessage/configure.zcml
ftw/globalstatusmessage/interfaces.py
ftw/globalstatusmessage/lawgiver.zcml
ftw/globalstatusmessage/permissions.zcml
ftw/globalstatusmessage/setuphandlers.py
ftw/globalstatusmessage/testing.py
ftw/globalstatusmessage/utils.py
ftw/globalstatusmessage/vocabularies.py
ftw/globalstatusmessage/Extensions/install.py
ftw/globalstatusmessage/browser/__init__.py
ftw/globalstatusmessage/browser/config.py
ftw/globalstatusmessage/browser/configure.zcml
ftw/globalstatusmessage/browser/controlpanel.py
ftw/globalstatusmessage/browser/publisher.py
ftw/globalstatusmessage/browser/viewlets/__init__.py
ftw/globalstatusmessage/browser/viewlets/statusmessage.pt
ftw/globalstatusmessage/browser/viewlets/statusmessage.py
ftw/globalstatusmessage/browser/viewlets/styles.pt
ftw/globalstatusmessage/locales/ftw.globalstatusmessage.pot
ftw/globalstatusmessage/locales/de/LC_MESSAGES/ftw.globalstatusmessage.po
ftw/globalstatusmessage/locales/es/LC_MESSAGES/ftw.globalstatusmessage.po
ftw/globalstatusmessage/locales/fi/LC_MESSAGES/ftw.globalstatusmessage.po
ftw/globalstatusmessage/locales/pt_BR/LC_MESSAGES/ftw.globalstatusmessage.po
ftw/globalstatusmessage/profiles/default/browserlayer.xml
ftw/globalstatusmessage/profiles/default/controlpanel.xml
ftw/globalstatusmessage/profiles/default/metadata.xml
ftw/globalstatusmessage/profiles/default/registry.xml
ftw/globalstatusmessage/profiles/default/rolemap.xml
ftw/globalstatusmessage/profiles/uninstall/browserlayer.xml
ftw/globalstatusmessage/profiles/uninstall/ftw.globalstatusmessage.various.txt
ftw/globalstatusmessage/profiles/uninstall/registry.xml
ftw/globalstatusmessage/profiles/uninstall/rolemap.xml
ftw/globalstatusmessage/tests/__init__.py
ftw/globalstatusmessage/tests/helpers.py
