Metadata-Version: 2.1
Name: ftw.globalstatusmessage
Version: 1.7.3
Summary: Shows a global message on every site.
Home-page: https://github.com/4teamwork/ftw.globalstatusmessage
Author: 4teamwork AG
Author-email: mailto:info@4teamwork.ch
License: GPL2
Keywords: ftw global status message plone
Platform: UNKNOWN
Classifier: Framework :: Plone
Classifier: Framework :: Plone :: 4.3
Classifier: Framework :: Plone :: 5.1
Classifier: Programming Language :: Python
Classifier: Topic :: Software Development :: Libraries :: Python Modules
Provides-Extra: tests
